{
  "session_id": "session-2026-05-05-0510",
  "started": "2026-05-05T09:10:39.731Z",
  "files_read": {
    "/home/runner/.maximizer/projects/moat/runs/20260505T083851Z-d3bb40/review.json": {
      "count": 1,
      "tokens": 0,
      "first_read": "2026-05-05T09:10:48.122Z"
    },
    "/home/runner/.maximizer/projects/moat/runs/20260505T083851Z-d3bb40/iteration.json": {
      "count": 1,
      "tokens": 0,
      "first_read": "2026-05-05T09:10:48.425Z"
    },
    "/home/runner/moat-research/docs/calibration/2026-05-05-n8-pass.md": {
      "count": 1,
      "tokens": 2391,
      "first_read": "2026-05-05T09:11:05.976Z"
    }
  },
  "files_written": [],
  "edit_counts": {},
  "anatomy_hits": 1,
  "anatomy_misses": 2,
  "repeated_reads_warned": 0,
  "cerebrum_warnings": 0,
  "stop_count": 1
}